{"_id":"1c6b09b6-e364-4587-baad-2c2559271feb","username":"superadmin","displayName":"Super Admin","roles":["super_admin"],"passwordHash":"$argon2id$v=19$m=65536,t=3,p=4$pmHmZ6qLVcjoq7sTi0ShDA$M84RmemVy2gzLeJnK0JCpem/Ms7fY/kogq2e/RuvQNg","forceChangeOnFirstLogin":false,"active":true,"createdAt":{"$date":{"$numberLong":"1781876059578"}},"updatedAt":{"$date":{"$numberLong":"1781941268731"}},"email":"blitznihar@gmail.com","emailConfirmed":true}
{"_id":"1fceda61-2d19-4107-9c64-57a78083f836","username":"admin","displayName":"Admin","roles":["admin"],"passwordHash":"$argon2id$v=19$m=65536,t=3,p=4$HGdw2Q2P6X3s6085tEqrfA$Ok8pHI3ZxLMn+WVSMtyNOqQR5WbyQJrHNpM50I/wLd8","forceChangeOnFirstLogin":true,"active":true,"createdAt":{"$date":{"$numberLong":"1781876059612"}},"updatedAt":{"$date":{"$numberLong":"1781941670168"}},"studentIds":[],"parentIds":["460616dd-3131-43a4-bec8-2101121847b9","ebcee2c3-a1e8-4f1c-85b1-f92ee23d2b73","0406fec9-e4e0-460d-9c2a-d833b268d344"],"email":"blitznihar@gmail.com","emailConfirmed":false}
{"_id":"16caa66e-d0ce-4271-a6d5-319bddf4bc95","username":"araina.malali","displayName":"Araina Malali","roles":["student"],"passwordHash":"$argon2id$v=19$m=65536,t=3,p=4$7rPrijt6+PH3GaF2Dx3Yjg$OY57yF5wjv9nWQ0i60oFDvRVjz7vuI16nOKCv4tJQI4","forceChangeOnFirstLogin":false,"active":true,"createdAt":{"$date":{"$numberLong":"1781924775668"}},"updatedAt":{"$date":{"$numberLong":"1781941712323"}},"email":"araina.malali@gmail.com","emailConfirmed":true,"parentIds":[],"studentIds":[]}
{"_id":"0406fec9-e4e0-460d-9c2a-d833b268d344","username":"sushma.malali","displayName":"Sushma Malali","roles":["parent"],"studentIds":["16caa66e-d0ce-4271-a6d5-319bddf4bc95"],"parentIds":[],"passwordHash":"$argon2id$v=19$m=65536,t=3,p=4$HGdw2Q2P6X3s6085tEqrfA$Ok8pHI3ZxLMn+WVSMtyNOqQR5WbyQJrHNpM50I/wLd8","forceChangeOnFirstLogin":true,"active":true,"createdAt":{"$date":{"$numberLong":"1781930640351"}},"updatedAt":{"$date":{"$numberLong":"1781941670162"}},"email":"sushnihar@gmail.com","emailConfirmed":false}
